<?xml version="1.0" encoding="UTF-8"?><extraction><clueid>118894871</clueid><fullpath><![CDATA[https://github.com/irccloud/android/commit/c6d73e97faec5f99653268bd95f82bf351c96ec6]]></fullpath><realpath><![CDATA[https://github.com/irccloud/android/commit/c6d73e97faec5f99653268bd95f82bf351c96ec6]]></realpath><theme>irccloudCommit_item</theme><middle>default</middle><createdate>2015-8-24 18:27:2</createdate><baseURI><bucketBaseURI><bucketName>Commit</bucketName><uri><![CDATA[https://github.com/irccloud/android/commit/c6d73e97faec5f99653268bd95f82bf351c96ec6]]></uri></bucketBaseURI></baseURI>
<Commit><item><title>
      Prompt for channel key if required
    </title><numbercommit>
      2 changed files
    </numbercommit><source_file><item><name>
              src/com/irccloud/android/NetworkConnection.java
            </name></item><item><name/></item></source_file></item></Commit></extraction>