<?xml version="1.0" encoding="UTF-8"?><extraction><clueid>118894051</clueid><fullpath><![CDATA[https://github.com/irccloud/android/commit/fff16e1598d112766b92254ecef7e0a57c0e791a]]></fullpath><realpath><![CDATA[https://github.com/irccloud/android/commit/fff16e1598d112766b92254ecef7e0a57c0e791a]]></realpath><theme>irccloudCommit_item</theme><middle>default</middle><createdate>2015-8-24 18:1:36</createdate><baseURI><bucketBaseURI><bucketName>Commit</bucketName><uri><![CDATA[https://github.com/irccloud/android/commit/fff16e1598d112766b92254ecef7e0a57c0e791a]]></uri></bucketBaseURI></baseURI>
<Commit><item><title>
      Use a lighter blue link color on pending and collapsed messages
    </title><numbercommit>
      2 changed files
    </numbercommit><source_file><item><name>
              src/com/irccloud/android/MessageViewFragment.java
            </name></item><item><name/></item></source_file></item></Commit></extraction>