<?xml version="1.0" encoding="UTF-8"?><extraction><clueid>118893631</clueid><fullpath><![CDATA[https://github.com/irccloud/android/commit/74816cf0871c73bb4e652c773eff106884ed8a30]]></fullpath><realpath><![CDATA[https://github.com/irccloud/android/commit/74816cf0871c73bb4e652c773eff106884ed8a30]]></realpath><theme>irccloudCommit_item</theme><middle>default</middle><createdate>2015-8-24 17:45:46</createdate><baseURI><bucketBaseURI><bucketName>Commit</bucketName><uri><![CDATA[https://github.com/irccloud/android/commit/74816cf0871c73bb4e652c773eff106884ed8a30]]></uri></bucketBaseURI></baseURI>
<Commit><item><title>
      Fix the image viewer styling on Android 5
    </title><numbercommit>
      3 changed files
    </numbercommit><source_file><item><name>
              res/values-v19/styles.xml
            </name></item><item><name>
              res/values-v21/styles.xml
            </name></item><item><name/></item></source_file></item></Commit></extraction>